fpl/__init__.py
fpl/cli.py
fpl/constants.py
fpl/fpl.py
fpl/utils.py
fpl/models/__init__.py
fpl/models/classic_league.py
fpl/models/fixture.py
fpl/models/gameweek.py
fpl/models/h2h_league.py
fpl/models/player.py
fpl/models/team.py
fpl/models/user.py
tests/__init__.py
tests/conftest.py
tests/helper.py
tests/temp_env_var.py
tests/test_classic_league.py
tests/test_fixture.py
tests/test_fpl.py
tests/test_gameweek.py
tests/test_h2h_league.py
tests/test_player.py
tests/test_settings.py
tests/test_team.py
tests/test_user.py
tests/test_utils.py
fpl-0.6.35.dist-info/AUTHORS.rst
fpl-0.6.35.dist-info/LICENSE.txt
fpl-0.6.35.dist-info/METADATA
fpl-0.6.35.dist-info/WHEEL
fpl-0.6.35.dist-info/entry_points.txt
fpl-0.6.35.dist-info/top_level.txt
fpl-0.6.35.dist-info/RECORD
