Metadata-Version: 2.1
Name: fpl
Version: 0.6.35
Summary: A Python wrapper for the Fantasy Premier League API
Home-page: https://github.com/amosbastian/fpl
Author: amosbastian
Author-email: amosbastian@gmail.com
License: MIT
Project-URL: Documentation, http://fpl.readthedocs.io/en/latest/
Project-URL: Source, https://github.com/amosbastian/fpl
Keywords: fpl fantasy premier league
Classifier: Development Status :: 4 - Beta
Classifier: Intended Audience :: Developers
Classifier: License :: OSI Approved :: MIT License
Classifier: Programming Language :: Python :: 3.6
Classifier: Programming Language :: Python :: 3.7
License-File: LICENSE.txt
License-File: AUTHORS.rst
